geokey_airquality
travis_ci
