Metadata-Version: 1.1
Name: geokey-airquality
Version: 1.2.1
Summary: GeoKey extension for Air Quality functionality
Home-page: https://github.com/ExCiteS/geokey-airquality
Author: Mapping for Change
Author-email: info@mappingforchange.org.uk
License: MIT
Download-URL: https://github.com/ExCiteS/geokey-airquality/tarball/1.2.1
Platform: UNKNOWN
